certsling/__init__.py
certsling/acme.py
certsling/acmesession.py
certsling/servers.py
certsling/utils.py
certsling-0.10.0.dist-info/METADATA
certsling-0.10.0.dist-info/WHEEL
certsling-0.10.0.dist-info/entry_points.txt
certsling-0.10.0.dist-info/top_level.txt
certsling-0.10.0.dist-info/RECORD
