Metadata-Version: 2.1
Name: certsling
Version: 0.10.0
Summary: Opinionated letsencrypt acme client working via a ssh port forward.
Home-page: https://github.com/fschulze/certsling
License: UNKNOWN
Platform: UNKNOWN
Classifier: Development Status :: 4 - Beta
Classifier: Intended Audience :: System Administrators
Classifier: License :: OSI Approved :: MIT License
Classifier: Programming Language :: Python
Classifier: Programming Language :: Python :: 3 :: Only
Classifier: Programming Language :: Python :: 3.7
Classifier: Programming Language :: Python :: 3.8
Classifier: Programming Language :: Python :: 3.9
Classifier: Programming Language :: Python :: 3.10
Requires-Python: >=3.7
Requires-Dist: click
Requires-Dist: dnspython (>=1.15.0)
Requires-Dist: pyOpenSSL
Requires-Dist: requests
